flask_dependant/__init__.py
flask_dependant/app.py
flask_dependant/dependant.py
flask_dependant/exception_handlers.py
flask_dependant/exceptions.py
flask_dependant/models.py
flask_dependant/params.py
flask_dependant/response.py
flask_dependant/utils.py
flask_dependant-1.0.1.dist-info/METADATA
flask_dependant-1.0.1.dist-info/WHEEL
flask_dependant-1.0.1.dist-info/top_level.txt
flask_dependant-1.0.1.dist-info/RECORD
