Metadata-Version: 2.1
Name: flask-dependant
Version: 1.0.1
Summary: Flask Dependant is a Dependency Injection Helper Which Same With FastApi Dependencies, Pydantic and Python 3.6+ type hints.
Home-page: UNKNOWN
Author: xiaojiang
Maintainer: xiaojiang
License: MIT
Platform: all
Classifier: Development Status :: 4 - Beta
Classifier: Operating System :: OS Independent
Classifier: Intended Audience :: Developers
Classifier: License :: OSI Approved :: MIT License
Classifier: Programming Language :: Python :: 3.6
Classifier: Programming Language :: Python :: 3.7
Classifier: Programming Language :: Python :: 3.8
Classifier: Programming Language :: Python :: 3.9
Classifier: Topic :: Software Development :: Libraries
Requires-Python: >=3.6
Requires-Dist: flask (>=2.0)
Requires-Dist: pydantic (<2.0.0,>=1.8)
